ip138/__init__.py
ip138/cmdline.py
ip138/command.py
ip138/constant.py
ip138/ip138.py
ip138/logger.py
ip138-0.0.1.dist-info/LICENSE
ip138-0.0.1.dist-info/METADATA
ip138-0.0.1.dist-info/WHEEL
ip138-0.0.1.dist-info/entry_points.txt
ip138-0.0.1.dist-info/top_level.txt
ip138-0.0.1.dist-info/RECORD
