Metadata-Version: 2.1
Name: ip138
Version: 0.0.1
Summary: ip138.com comics downloader
Home-page: https://github.com/KellyHwong/ip138
Author: KellyHwong
Author-email: dianhuangkan@gmail.com
Maintainer: KellyHwong
Maintainer-email: dianhuangkan@gmail.com
License: MIT
Keywords: ip138,comics
Platform: all
Classifier: Development Status :: 3 - Alpha
Classifier: Environment :: Web Environment
Classifier: Intended Audience :: Developers
Classifier: License :: OSI Approved :: MIT License
Classifier: Operating System :: OS Independent
Classifier: Programming Language :: Python :: 3.6
Classifier: Programming Language :: Python :: 3.7
Classifier: Topic :: Internet :: WWW/HTTP
Classifier: Topic :: Software Development :: Libraries :: Python Modules
Requires-Dist: requests (>=2.5.0)
Requires-Dist: BeautifulSoup4 (>=4.0.0)
Requires-Dist: future (>=0.15.2)
Requires-Dist: lxml (>=4.2.0)
